{
  "contributors": [
    {
      "name": "Francis Taylor",
      "username": "Git: @Fr4ncisTaylor",
      "bio": "Developer of PC Health. Python & Qt enthusiast.",
      "image": "files/images/profile.jpg",
      "button1_value": "https://github.com/Fr4ncisTaylor",
      "button2_value": "https://instagram.com/slash.baiano"
    },
    {
      "name": "",
      "username": "",
      "bio": "",
      "image": "files/images/you_profile_pic.jpg",
      "button1_value": "git",
      "button2_value": "insta"
    }
  ]
}